DiscoverVersion/__init__.py
DiscoverVersion/__main__.py
DiscoverVersion/discovery.py
DiscoverVersion/meson_python.py
DiscoverVersion/version.py
discoverversion-0.4.0.dist-info/entry_points.txt
discoverversion-0.4.0.dist-info/licenses/LICENSE.md
discoverversion-0.4.0.dist-info/WHEEL
discoverversion-0.4.0.dist-info/METADATA
discoverversion-0.4.0.dist-info/RECORD
