Metadata-Version: 2.4
Name: DiscoverVersion
Version: 0.4.0
Summary: Version discovery for Python packages
Keywords: version,versioning,git,setuptools_scm,setuptools-scm,scm,meson,meson-python,flit,packaging,build
Author-email: Lars Pastewka <lars.pastewka@imtek.uni-freiburg.de>
Requires-Python: >=3.8.0
Classifier: Development Status :: 4 - Beta
Classifier: Intended Audience :: Developers
Classifier: License :: OSI Approved :: MIT License
Classifier: Programming Language :: Python
Classifier: Programming Language :: Python :: 3
Classifier: Programming Language :: Python :: 3.8
Classifier: Programming Language :: Python :: 3.9
Classifier: Programming Language :: Python :: 3.10
Classifier: Programming Language :: Python :: 3.11
Classifier: Programming Language :: Python :: 3.12
Classifier: Programming Language :: Python :: 3.13
Classifier: Topic :: Software Development :: Build Tools
Classifier: Topic :: Software Development :: Version Control :: Git
License-File: LICENSE.md
Requires-Dist: flake8 ; extra == "test"
Requires-Dist: pytest ; extra == "test"
Requires-Dist: pytest-cov ; extra == "test"
Requires-Dist: pytest-flake8 ; extra == "test"
Project-URL: changelog, https://github.com/imtek-simulation/DiscoverVersion/blob/master/CHANGELOG.md
Project-URL: documentation, https://imtek-simulation.github.io/DiscoverVersion/
Project-URL: repository, https://github.com/imtek-simulation/DiscoverVersion
Provides-Extra: test
